timedinput/__init__.py
timedinput/timedinput.py
timedinput-0.1.0.dist-info/LICENSE
timedinput-0.1.0.dist-info/METADATA
timedinput-0.1.0.dist-info/WHEEL
timedinput-0.1.0.dist-info/top_level.txt
timedinput-0.1.0.dist-info/RECORD
