Metadata-Version: 2.1
Name: timedinput
Version: 0.1.0
Summary: Timeout for python inputs
Author-email: Kerollos Emad <kerollos.em@gmail.com>
License: MIT License
Project-URL: Source, https://github.com/kerollosy/timedinput
Project-URL: Bug Tracker, https://github.com/kerollosy/timedinput/issues
Keywords: input,stdin,timeout,console
Classifier: Programming Language :: Python :: 3
Classifier: Intended Audience :: Developers
Classifier: Environment :: Console
Classifier: Topic :: Software Development :: Libraries :: Python Modules
Classifier: License :: OSI Approved :: MIT License
Classifier: Operating System :: POSIX :: Linux
Classifier: Operating System :: Microsoft :: Windows
Classifier: Operating System :: MacOS
License-File: LICENSE
